{"v":"2.2","w":375,"h":560,"fps":30,"bg":"#0d0d26","mc":false,"f":[[{"l":0,"s":0,"e":8}],[{"l":0,"s":0,"e":16}],[{"l":0,"s":0,"e":24}],[{"l":0,"s":0,"e":32}],[{"l":0,"s":0,"e":40}],[{"l":0,"s":0,"e":48}],[{"l":0,"s":0,"e":56}],[{"l":0,"s":0,"e":64}],[{"l":0,"s":0,"e":72}],[{"l":0,"s":0,"e":80}],[{"l":0,"s":0,"e":88}],[{"l":0,"s":0,"e":96}],[{"l":0,"s":0,"e":104}],[{"l":0,"s":0,"e":112}],[{"l":0,"s":0,"e":120}],[{"l":0,"s":0,"e":128}],[{"l":0,"s":0,"e":136}],[{"l":0,"s":0,"e":144}],[{"l":0,"s":0,"e":152}],[{"l":0,"s":0,"e":160}],[{"l":0,"s":0,"e":168}],[{"l":0,"s":0,"e":176}],[{"l":0,"s":0,"e":184}],[{"l":0,"s":0,"e":192}],[{"l":0,"s":0,"e":200}],[{"l":0,"s":0,"e":208}],[{"l":0,"s":0,"e":216}],[{"l":0,"s":0,"e":224}],[{"l":0,"s":0,"e":232}],[{"l":0,"s":0,"e":240}],[{"l":0,"s":0,"e":248}],[{"l":0,"s":0,"e":256}],[{"l":0,"s":0,"e":264}],[{"l":0,"s":0,"e":272}],[{"l":0,"s":0,"e":280}],[{"l":0,"s":0,"e":288}],[{"l":0,"s":0,"e":296}],[{"l":0,"s":0,"e":304}],[{"l":0,"s":0,"e":312}],[{"l":0,"s":0,"e":320}],[{"l":0,"s":0,"e":328}],[{"l":0,"s":0,"e":336}],[{"l":0,"s":0,"e":344}],[{"l":0,"s":0,"e":352}],[{"l":0,"s":0,"e":360}],[{"l":0,"s":0,"e":368}],[{"l":0,"s":0,"e":376}],[{"l":0,"s":0,"e":384}],[{"l":0,"s":0,"e":392}],[{"l":0,"s":0,"e":400}],[{"l":0,"s":0,"e":408}],[{"l":0,"s":0,"e":416}],[{"l":0,"s":0,"e":424}],[{"l":0,"s":0,"e":432}],[{"l":0,"s":0,"e":440}],[{"l":0,"s":0,"e":448}],[{"l":0,"s":0,"e":456}],[{"l":0,"s":0,"e":464}],[{"l":0,"s":0,"e":472}],[{"l":0,"s":0,"e":480}],[{"l":0,"s":0,"e":488}],[{"l":0,"s":0,"e":496}],[{"l":0,"s":0,"e":504}],[{"l":0,"s":0,"e":512}],[{"l":0,"s":0,"e":520}],[{"l":0,"s":0,"e":528}],[{"l":0,"s":0,"e":536}],[{"l":0,"s":0,"e":544}],[{"l":0,"s":0,"e":552}],[{"l":0,"s":0,"e":560}],[{"l":0,"s":0,"e":568}],[{"l":0,"s":0,"e":576}],[{"l":0,"s":0,"e":584}],[{"l":0,"s":0,"e":592}],[{"l":0,"s":0,"e":600}],[{"l":0,"s":0,"e":608}],[{"l":0,"s":0,"e":616}],[{"l":0,"s":0,"e":624}],[{"l":0,"s":0,"e":632}],[{"l":0,"s":0,"e":640}],[{"l":1}],[{"l":1,"s":0,"e":645}],[{"l":1,"s":14,"e":645}],[{"l":1,"s":28,"e":645}],[{"l":1,"s":42,"e":645}],[{"l":1,"s":56,"e":645}],[{"l":1,"s":70,"e":645}],[{"l":1,"s":84,"e":645}],[{"l":1,"s":98,"e":645}],[{"l":1,"s":112,"e":645}],[{"l":1,"s":126,"e":645}],[{"l":1,"s":140,"e":645}],[{"l":1,"s":154,"e":645}],[{"l":1,"s":168,"e":645}],[{"l":1,"s":182,"e":645}],[{"l":1,"s":196,"e":645}],[{"l":1,"s":210,"e":645}],[{"l":1,"s":224,"e":645}],[{"l":1,"s":238,"e":645}],[{"l":1,"s":252,"e":645}],[{"l":1,"s":266,"e":645}],[{"l":1,"s":280,"e":645}],[{"l":1,"s":294,"e":645}],[{"l":1,"s":308,"e":645}],[{"l":1,"s":322,"e":645}],[{"l":1,"s":336,"e":645}],[{"l":1,"s":350,"e":645}],[{"l":1,"s":364,"e":645}],[{"l":1,"s":378,"e":645}],[{"l":1,"s":392,"e":645}],[{"l":1,"s":406,"e":645}],[{"l":1,"s":420,"e":645}],[{"l":1,"s":434,"e":645}],[{"l":1,"s":448,"e":645}],[{"l":1,"s":462,"e":645}],[{"l":1,"s":476,"e":645}],[{"l":1,"s":490,"e":645}],[{"l":1,"s":504,"e":645}],[{"l":1,"s":518,"e":645}],[{"l":1,"s":532,"e":645}],[{"l":1,"s":546,"e":645}],[{"l":1,"s":560,"e":645}],[{"l":1,"s":574,"e":645}],[{"l":1,"s":588,"e":645}],[{"l":1,"s":602,"e":645}],[{"l":1,"s":616,"e":645}],[{"l":1,"s":630,"e":645}],[{"l":1,"s":644,"e":645}]],"l":[{"d":0,"s":0,"e":645,"c":"#ffffff","n":2,"r":1,"w":1,"v":0.1,"x":0,"y":0},{"d":0,"s":0,"e":645,"c":"#ffffff","n":2,"r":1,"w":1,"v":0.1,"x":0,"y":0}],"d":[[{"x":86,"y":81},{"x":86,"y":82},{"x":86,"y":83},{"x":86,"y":89},{"x":86,"y":96},{"x":87,"y":104},{"x":91,"y":110},{"x":92,"y":112},{"x":97,"y":111},"end",{"x":77,"y":97},{"x":77,"y":97},{"x":80,"y":97},{"x":89,"y":97},{"x":91,"y":97},"end",{"x":104,"y":96},{"x":104,"y":96},{"x":105,"y":100},{"x":105,"y":104},{"x":105,"y":108},{"x":105,"y":109},{"x":105,"y":109},{"x":107,"y":103},{"x":110,"y":99},{"x":112,"y":97},"end",{"x":120,"y":101},{"x":120,"y":101},{"x":120,"y":102},{"x":120,"y":107},{"x":123,"y":112},"end",{"x":129,"y":99},{"x":129,"y":99},{"x":129,"y":103},{"x":129,"y":108},{"x":125,"y":117},{"x":122,"y":122},{"x":122,"y":123},{"x":121,"y":123},"end",{"x":156,"y":89},{"x":156,"y":89},{"x":156,"y":91},{"x":156,"y":97},{"x":154,"y":107},{"x":153,"y":111},{"x":155,"y":113},{"x":157,"y":114},{"x":161,"y":114},"end",{"x":149,"y":102},{"x":149,"y":102},{"x":157,"y":102},{"x":163,"y":102},"end",{"x":171,"y":94},{"x":171,"y":94},{"x":173,"y":97},{"x":174,"y":107},{"x":172,"y":113},{"x":173,"y":115},{"x":173,"y":114},{"x":174,"y":112},{"x":176,"y":108},{"x":178,"y":107},{"x":182,"y":107},{"x":183,"y":111},{"x":183,"y":116},{"x":182,"y":118},{"x":182,"y":117},"end",{"x":190,"y":112},{"x":190,"y":112},{"x":196,"y":111},{"x":198,"y":109},{"x":196,"y":107},{"x":192,"y":108},{"x":190,"y":112},{"x":190,"y":117},{"x":194,"y":118},{"x":202,"y":118},"end",{"x":232,"y":110},{"x":232,"y":110},{"x":231,"y":114},{"x":233,"y":120},{"x":234,"y":127},{"x":234,"y":130},{"x":234,"y":128},{"x":234,"y":122},{"x":235,"y":116},{"x":238,"y":113},{"x":241,"y":113},{"x":245,"y":117},{"x":245,"y":124},{"x":247,"y":129},{"x":246,"y":133},{"x":245,"y":134},{"x":247,"y":131},"end",{"x":254,"y":115},{"x":254,"y":114},{"x":257,"y":114},{"x":261,"y":117},{"x":261,"y":122},{"x":261,"y":129},{"x":261,"y":130},{"x":261,"y":127},{"x":259,"y":123},{"x":254,"y":122},{"x":254,"y":122},{"x":254,"y":128},{"x":254,"y":132},{"x":256,"y":133},{"x":262,"y":132},"end",{"x":271,"y":117},{"x":271,"y":117},{"x":271,"y":122},{"x":272,"y":130},{"x":272,"y":133},{"x":273,"y":132},{"x":276,"y":126},{"x":276,"y":120},{"x":278,"y":118},{"x":279,"y":119},{"x":281,"y":126},{"x":281,"y":131},{"x":282,"y":132},{"x":282,"y":131},{"x":284,"y":125},{"x":287,"y":119},{"x":290,"y":118},{"x":292,"y":119},{"x":294,"y":125},{"x":294,"y":132},{"x":293,"y":135},{"x":293,"y":136},{"x":294,"y":135},"end",{"x":303,"y":128},{"x":303,"y":128},{"x":307,"y":128},{"x":310,"y":126},{"x":311,"y":123},{"x":308,"y":120},{"x":306,"y":121},{"x":304,"y":127},{"x":303,"y":131},{"x":304,"y":134},{"x":306,"y":136},{"x":312,"y":136},{"x":313,"y":136},"end",{"x":125,"y":173},{"x":125,"y":173},{"x":124,"y":173},{"x":123,"y":173},{"x":118,"y":174},{"x":115,"y":176},{"x":114,"y":182},{"x":117,"y":187},{"x":122,"y":188},{"x":130,"y":186},{"x":134,"y":182},{"x":134,"y":180},{"x":130,"y":177},{"x":124,"y":175},{"x":121,"y":174},{"x":120,"y":174},"end",{"x":144,"y":165},{"x":144,"y":165},{"x":139,"y":163},{"x":137,"y":163},{"x":137,"y":165},{"x":138,"y":172},{"x":140,"y":179},{"x":141,"y":188},{"x":141,"y":192},{"x":142,"y":191},{"x":145,"y":189},"end",{"x":134,"y":182},{"x":134,"y":182},{"x":143,"y":180},{"x":147,"y":180},{"x":147,"y":180},"end",{"x":191,"y":180},{"x":191,"y":180},{"x":189,"y":185},{"x":188,"y":194},{"x":189,"y":199},{"x":191,"y":201},{"x":196,"y":201},{"x":196,"y":202},{"x":202,"y":200},"end",{"x":184,"y":191},{"x":184,"y":191},{"x":192,"y":191},{"x":195,"y":191},"end",{"x":208,"y":182},{"x":208,"y":182},{"x":207,"y":187},{"x":209,"y":195},{"x":209,"y":202},{"x":210,"y":202},{"x":210,"y":200},{"x":213,"y":194},{"x":216,"y":193},{"x":218,"y":194},{"x":219,"y":199},{"x":221,"y":204},{"x":221,"y":206},{"x":223,"y":203},"end",{"x":229,"y":197},{"x":229,"y":197},{"x":233,"y":197},{"x":237,"y":197},{"x":241,"y":194},{"x":241,"y":192},{"x":234,"y":191},{"x":231,"y":194},{"x":230,"y":200},{"x":232,"y":204},{"x":237,"y":206},{"x":246,"y":205},{"x":246,"y":205},"end",{"x":107,"y":248},{"x":107,"y":248},{"x":105,"y":245},{"x":103,"y":243},{"x":99,"y":241},{"x":96,"y":242},{"x":94,"y":244},{"x":94,"y":251},{"x":95,"y":261},{"x":99,"y":269},{"x":102,"y":272},{"x":103,"y":273},{"x":104,"y":273},{"x":106,"y":272},"end",{"x":96,"y":262},{"x":96,"y":262},{"x":98,"y":262},{"x":104,"y":262},{"x":110,"y":260},"end",{"x":121,"y":256},{"x":121,"y":256},{"x":121,"y":258},{"x":123,"y":266},{"x":124,"y":270},{"x":124,"y":269},{"x":124,"y":264},"end",{"x":118,"y":249},{"x":119,"y":249},{"x":118,"y":249},{"x":119,"y":247},"end",{"x":133,"y":254},{"x":133,"y":254},{"x":135,"y":259},{"x":135,"y":265},{"x":136,"y":268},{"x":137,"y":265},{"x":137,"y":260},{"x":137,"y":255},{"x":141,"y":252},"end",{"x":159,"y":251},{"x":159,"y":251},{"x":154,"y":252},{"x":148,"y":255},{"x":148,"y":255},{"x":155,"y":257},{"x":160,"y":260},{"x":160,"y":265},{"x":159,"y":265},{"x":156,"y":265},{"x":152,"y":265},"end",{"x":169,"y":243},{"x":170,"y":243},{"x":169,"y":247},{"x":169,"y":254},{"x":169,"y":260},{"x":171,"y":264},{"x":173,"y":266},{"x":175,"y":266},{"x":180,"y":265},"end",{"x":165,"y":256},{"x":165,"y":256},{"x":164,"y":255},{"x":164,"y":255},{"x":167,"y":255},{"x":174,"y":254},"end",{"x":228,"y":246},{"x":223,"y":245},{"x":219,"y":244},{"x":214,"y":247},{"x":212,"y":251},{"x":212,"y":259},{"x":212,"y":269},{"x":215,"y":278},{"x":216,"y":281},{"x":217,"y":283},{"x":217,"y":283},"end",{"x":211,"y":272},{"x":211,"y":272},{"x":218,"y":272},{"x":219,"y":271},"end",{"x":231,"y":274},{"x":231,"y":274},{"x":233,"y":278},{"x":234,"y":281},{"x":234,"y":281},{"x":234,"y":274},{"x":234,"y":271},{"x":236,"y":270},"end",{"x":245,"y":270},{"x":244,"y":270},{"x":245,"y":274},{"x":246,"y":278},{"x":246,"y":280},{"x":246,"y":279},"end",{"x":242,"y":259},{"x":242,"y":259},{"x":244,"y":259},"end",{"x":254,"y":271},{"x":254,"y":271},{"x":256,"y":271},{"x":258,"y":271},{"x":260,"y":270},{"x":259,"y":267},{"x":255,"y":267},{"x":253,"y":270},{"x":253,"y":273},{"x":253,"y":278},{"x":255,"y":280},{"x":259,"y":279},{"x":260,"y":277},"end",{"x":268,"y":267},{"x":268,"y":267},{"x":268,"y":271},{"x":268,"y":277},{"x":268,"y":281},{"x":269,"y":281},{"x":269,"y":279},{"x":270,"y":273},{"x":272,"y":270},{"x":274,"y":270},{"x":276,"y":271},{"x":278,"y":275},{"x":278,"y":279},{"x":278,"y":282},{"x":278,"y":282},{"x":279,"y":281},"end",{"x":291,"y":269},{"x":292,"y":269},{"x":289,"y":269},{"x":285,"y":270},{"x":284,"y":273},{"x":283,"y":277},{"x":287,"y":278},{"x":293,"y":277},{"x":295,"y":275},"end",{"x":295,"y":252},{"x":295,"y":252},{"x":294,"y":257},{"x":294,"y":267},{"x":294,"y":279},{"x":294,"y":286},{"x":296,"y":288},{"x":296,"y":288},"end",{"x":102,"y":326},{"x":102,"y":326},{"x":102,"y":326},{"x":103,"y":330},{"x":103,"y":336},{"x":107,"y":340},{"x":110,"y":338},{"x":116,"y":334},{"x":115,"y":331},{"x":114,"y":331},{"x":114,"y":331},{"x":116,"y":334},{"x":119,"y":337},{"x":123,"y":337},{"x":127,"y":333},{"x":126,"y":329},{"x":124,"y":328},{"x":124,"y":328},"end",{"x":130,"y":316},{"x":130,"y":316},{"x":132,"y":320},{"x":134,"y":328},{"x":134,"y":335},{"x":136,"y":337},{"x":136,"y":337},{"x":138,"y":332},{"x":140,"y":328},{"x":143,"y":327},{"x":143,"y":330},{"x":145,"y":336},{"x":145,"y":339},{"x":145,"y":339},{"x":146,"y":339},"end",{"x":159,"y":330},{"x":159,"y":330},{"x":157,"y":333},{"x":157,"y":337},{"x":160,"y":337},{"x":166,"y":335},{"x":167,"y":334},{"x":166,"y":333},{"x":164,"y":330},{"x":160,"y":328},{"x":155,"y":329},{"x":154,"y":332},"end",{"x":153,"y":358},{"x":153,"y":358},{"x":153,"y":359},{"x":156,"y":357},{"x":163,"y":355},{"x":164,"y":356},{"x":167,"y":361},{"x":167,"y":368},{"x":167,"y":370},{"x":166,"y":370},{"x":166,"y":369},{"x":161,"y":366},{"x":155,"y":364},{"x":153,"y":365},{"x":154,"y":367},{"x":157,"y":369},{"x":161,"y":369},{"x":164,"y":369},{"x":168,"y":366},"end",{"x":177,"y":347},{"x":177,"y":347},{"x":177,"y":349},{"x":179,"y":357},{"x":179,"y":367},{"x":178,"y":370},{"x":178,"y":370},{"x":178,"y":369},{"x":178,"y":364},{"x":181,"y":359},{"x":187,"y":358},{"x":189,"y":361},{"x":190,"y":366},{"x":187,"y":370},{"x":184,"y":370},{"x":182,"y":370},{"x":180,"y":367},"end",{"x":197,"y":354},{"x":197,"y":354},{"x":202,"y":354},{"x":204,"y":357},{"x":204,"y":364},{"x":203,"y":366},{"x":202,"y":366},{"x":200,"y":363},{"x":198,"y":360},{"x":196,"y":360},{"x":196,"y":363},{"x":197,"y":367},{"x":199,"y":367},{"x":202,"y":366},"end",{"x":212,"y":353},{"x":212,"y":353},{"x":212,"y":356},{"x":212,"y":363},{"x":212,"y":368},{"x":212,"y":368},{"x":212,"y":368},{"x":212,"y":368},{"x":213,"y":362},{"x":214,"y":356},{"x":219,"y":354},{"x":223,"y":353},{"x":228,"y":354},{"x":229,"y":359},{"x":229,"y":365},{"x":228,"y":369},{"x":228,"y":371},{"x":228,"y":370},"end",{"x":245,"y":355},{"x":245,"y":354},{"x":245,"y":354},{"x":242,"y":354},{"x":240,"y":354},{"x":240,"y":357},{"x":239,"y":361},{"x":239,"y":365},{"x":240,"y":365},{"x":243,"y":365},{"x":246,"y":363},"end",{"x":250,"y":335},{"x":250,"y":335},{"x":250,"y":340},{"x":250,"y":349},{"x":250,"y":360},{"x":250,"y":364},{"x":251,"y":367},{"x":251,"y":367},{"x":251,"y":367},"end",{"x":265,"y":353},{"x":265,"y":353},{"x":265,"y":354},{"x":262,"y":359},{"x":261,"y":363},{"x":267,"y":365},{"x":273,"y":361},{"x":275,"y":359},{"x":272,"y":355},{"x":269,"y":353},{"x":267,"y":351},{"x":266,"y":352},"end",{"x":278,"y":353},{"x":278,"y":352},{"x":279,"y":352},{"x":279,"y":355},{"x":279,"y":360},{"x":279,"y":363},{"x":280,"y":363},{"x":282,"y":359},{"x":283,"y":354},{"x":287,"y":350},{"x":288,"y":350},{"x":290,"y":351},{"x":290,"y":357},{"x":290,"y":362},{"x":290,"y":366},{"x":290,"y":366},{"x":290,"y":364},"end",{"x":299,"y":355},{"x":299,"y":355},{"x":300,"y":356},{"x":303,"y":356},{"x":307,"y":353},{"x":308,"y":351},{"x":304,"y":350},{"x":302,"y":350},{"x":300,"y":353},{"x":299,"y":357},{"x":298,"y":362},{"x":300,"y":364},{"x":304,"y":364},{"x":306,"y":362},"end",{"x":323,"y":352},{"x":323,"y":352},{"x":320,"y":351},{"x":317,"y":353},{"x":316,"y":355},{"x":316,"y":358},{"x":317,"y":359},{"x":321,"y":359},{"x":324,"y":358},"end",{"x":326,"y":336},{"x":326,"y":336},{"x":325,"y":338},{"x":324,"y":348},{"x":322,"y":359},{"x":321,"y":368},{"x":321,"y":372},{"x":321,"y":373},{"x":319,"y":375},"end",{"x":159,"y":411},{"x":159,"y":411},{"x":159,"y":412},{"x":163,"y":420},{"x":165,"y":424},{"x":165,"y":425},"end",{"x":173,"y":409},{"x":171,"y":413},{"x":170,"y":420},{"x":168,"y":429},{"x":166,"y":439},{"x":166,"y":439},{"x":166,"y":438},"end",{"x":181,"y":415},{"x":181,"y":415},{"x":180,"y":418},{"x":179,"y":421},{"x":182,"y":424},{"x":186,"y":420},{"x":187,"y":416},{"x":184,"y":415},{"x":181,"y":414},{"x":181,"y":414},"end",{"x":198,"y":413},{"x":198,"y":413},{"x":198,"y":417},{"x":197,"y":420},{"x":198,"y":421},{"x":201,"y":421},{"x":204,"y":419},"end",{"x":208,"y":409},{"x":208,"y":409},{"x":208,"y":412},{"x":207,"y":420},{"x":206,"y":426},{"x":206,"y":427},{"x":206,"y":427},"end"]]}