{"v":"2.2","w":48,"h":64,"fps":30,"mc":false,"l":[{"d":0,"s":0,"e":122,"c":"ffffff","n":2,"r":1,"w":1,"v":0.1,"x":0,"y":0}],"f":[[{"l":0}]],"d":[[{"x":7,"y":7},{"x":7,"y":7},{"x":7,"y":7},{"x":7,"y":7},{"x":7,"y":7},{"x":7,"y":8},{"x":6,"y":11},{"x":6,"y":14},{"x":6,"y":17},{"x":6,"y":19},{"x":5,"y":22},{"x":5,"y":25},{"x":4,"y":27},{"x":4,"y":29},{"x":4,"y":31},{"x":4,"y":34},{"x":4,"y":36},{"x":4,"y":38},{"x":4,"y":40},{"x":4,"y":41},{"x":4,"y":43},{"x":4,"y":44},{"x":4,"y":46},{"x":4,"y":47},{"x":4,"y":48},{"x":4,"y":50},{"x":4,"y":52},{"x":5,"y":53},{"x":5,"y":54},{"x":5,"y":55},{"x":5,"y":56},{"x":6,"y":57},{"x":6,"y":58},{"x":7,"y":58},{"x":9,"y":58},{"x":11,"y":59},{"x":14,"y":59},{"x":16,"y":59},{"x":18,"y":59},{"x":20,"y":60},{"x":22,"y":60},{"x":24,"y":60},{"x":26,"y":60},{"x":27,"y":60},{"x":29,"y":60},{"x":30,"y":60},{"x":32,"y":60},{"x":34,"y":60},{"x":35,"y":60},{"x":36,"y":59},{"x":37,"y":59},{"x":38,"y":58},{"x":39,"y":57},{"x":40,"y":56},{"x":41,"y":54},{"x":42,"y":51},{"x":43,"y":48},{"x":43,"y":45},{"x":44,"y":41},{"x":44,"y":37},{"x":44,"y":33},{"x":44,"y":30},{"x":44,"y":26},{"x":44,"y":23},{"x":44,"y":19},{"x":44,"y":17},{"x":43,"y":15},{"x":43,"y":13},{"x":43,"y":11},{"x":42,"y":10},{"x":42,"y":9},{"x":41,"y":8},{"x":39,"y":7},{"x":36,"y":6},{"x":35,"y":6},{"x":33,"y":5},{"x":32,"y":5},{"x":30,"y":5},{"x":27,"y":5},{"x":24,"y":5},{"x":22,"y":5},{"x":18,"y":6},{"x":16,"y":6},{"x":14,"y":7},{"x":13,"y":7},{"x":11,"y":7},{"x":10,"y":7},{"x":9,"y":7},{"x":8,"y":7},{"x":8,"y":8},"end",{"x":17,"y":18},{"x":17,"y":18},{"x":17,"y":18},{"x":17,"y":20},{"x":17,"y":26},{"x":16,"y":31},{"x":16,"y":35},{"x":16,"y":38},{"x":16,"y":41},{"x":16,"y":43},{"x":16,"y":44},{"x":16,"y":44},{"x":16,"y":44},{"x":16,"y":44},"end",{"x":19,"y":18},{"x":19,"y":18},{"x":19,"y":18},{"x":23,"y":18},{"x":26,"y":18},{"x":28,"y":18},{"x":28,"y":18},"end",{"x":18,"y":33},{"x":18,"y":33},{"x":19,"y":34},{"x":21,"y":34},{"x":24,"y":34},{"x":25,"y":34},{"x":25,"y":33},"end"]]}